{
  "NONE": 0,
  "OFFSET": 1,
  "ASCII16": 2,
  "RTYPE": 3,
  "ASCII8": 4,
  "KOEI": 5,
  "WIZARDRY": 6,
  "KONAMI": 7,
  "FMPAC": 8,
  "GM2" : 9,
  "VY0010" : 10,
  "KONAMI_SCC" : 11,
  "MSX2_RAM" : 12,
  "GENRIC_16KB" : 13,
  "CROSS_BLAIM" : 14,
  "GENRIC_8KB" : 15,
  "HARRY_FOX" : 16,
  "ZEMINA80" : 17,
  "ZEMINA90" : 18,
  "KONAMI_SCC_PLUS" : 19,
  "MFRSD3" : 20,
  "MFRSD2" : 21,
  "MFRSD1" : 22,
  "MFRSD0" : 23,
  "NATIONAL" : 24,
  "ESE_RAM" : 25,
  "MEGARAM" : 26,
  "MEGASCC" : 27,
  "MEGAASCII8" : 28,
  "MEGAASCII16" : 29,
  "TURBO_R_FDC" : 30,
  "YAMAHA_SFG" : 31,
  "MIRROR" : 32,
  "SUPERSWANGI" : 33,
  "MSXWRITE" : 34
}
